license_reporter/__init__.py
license_reporter/__main__.py
license_reporter/cli.py
license_reporter/core.py
license_reporter/formatters.py
license_reporter/parsers.py
license_reporter-1.0.1.dist-info/METADATA
license_reporter-1.0.1.dist-info/WHEEL
license_reporter-1.0.1.dist-info/entry_points.txt
license_reporter-1.0.1.dist-info/licenses/LICENSE
license_reporter-1.0.1.dist-info/RECORD
