Metadata-Version: 2.4
Name: license-reporter
Version: 1.0.1
Summary: Universal Python License Report Generator for dependency compliance analysis
Project-URL: Homepage, https://github.com/yourusername/license-reporter
Project-URL: Documentation, https://license-reporter.readthedocs.io
Project-URL: Repository, https://github.com/yourusername/license-reporter.git
Project-URL: Bug Tracker, https://github.com/yourusername/license-reporter/issues
Project-URL: Changelog, https://github.com/yourusername/license-reporter/blob/main/CHANGELOG.md
Author-email: Ethan Li <aeon.zheng.li@gmail.com>
Maintainer-email: Ethan Li <aeon.zheng.li@gmail.com>
License: MIT License
License-File: LICENSE
Keywords: attribution,compliance,dependencies,legal,license,packages,pyinstaller,third-party
Classifier: Development Status :: 5 - Production/Stable
Classifier: Environment :: Console
Classifier: Intended Audience :: Developers
Classifier: Intended Audience :: Legal Industry
Classifier: License :: OSI Approved :: MIT License
Classifier: Operating System :: OS Independent
Classifier: Programming Language :: Python :: 3
Classifier: Programming Language :: Python :: 3.11
Classifier: Programming Language :: Python :: 3.12
Classifier: Programming Language :: Python :: 3.13
Classifier: Topic :: Software Development :: Libraries :: Python Modules
Classifier: Topic :: System :: Software Distribution
Classifier: Topic :: Utilities
Requires-Python: >=3.11
Requires-Dist: toml>=0.10.0
Provides-Extra: dev
Requires-Dist: black>=22.0.0; extra == 'dev'
Requires-Dist: flake8>=5.0.0; extra == 'dev'
Requires-Dist: isort>=5.10.0; extra == 'dev'
Requires-Dist: mypy>=1.0.0; extra == 'dev'
Requires-Dist: pre-commit>=2.20.0; extra == 'dev'
Requires-Dist: pytest-cov>=4.0.0; extra == 'dev'
Requires-Dist: pytest>=7.0.0; extra == 'dev'
Requires-Dist: pyyaml>=5.1.0; extra == 'dev'
Provides-Extra: docs
Requires-Dist: myst-parser>=0.18.0; extra == 'docs'
Requires-Dist: sphinx-rtd-theme>=1.0.0; extra == 'docs'
Requires-Dist: sphinx>=5.0.0; extra == 'docs'
Provides-Extra: enhanced
Requires-Dist: pyyaml>=5.1.0; extra == 'enhanced'
Provides-Extra: yaml
Requires-Dist: pyyaml>=5.1.0; extra == 'yaml'
